{"title": "CORNN: Convex optimization of recurrent neural networks for rapid inference of neural dynamics", "abstract": "Advances in optical and electrophysiological recording technologies have made it possible to record the dynamics of thousands of neurons, opening up new possibilities for interpreting and controlling large neural populations in behaving animals. A promising way to extract computational principles from these large datasets is to train data-constrained recurrent neural networks (dRNNs). Performing this training in real-time could open doors for research techniques and medical applications to model and control interventions at single-cell resolution and drive desired forms of animal behavior. However, existing training algorithms for dRNNs are inefficient and have limited scalability, making it a challenge to analyze large neural recordings even in offline scenarios. To address these issues, we introduce a training method termed Convex Optimization of Recurrent Neural Networks (CORNN). In studies of simulated recordings, CORNN attained training speeds $\\sim$100-fold faster than traditional optimization approaches while maintaining or enhancing modeling accuracy. We further validated CORNN on simulations with thousands of cells that performed simple computations such as those of a 3-bit flip-flop or the execution of a timed response. Finally, we showed that CORNN can robustly reproduce network dynamics and underlying attractor structures despite mismatches between generator and inference models, severe subsampling of observed neurons, or mismatches in neural time-scales. Overall, by training dRNNs with millions of parameters in subminute processing times on a standard computer, CORNN constitutes a first step towards real-time network reproduction constrained on large-scale neural recordings and a powerful computational tool for advancing the understanding of neural computation.", "id": "GGIA1p9fDT", "authors": ["Fatih Dinc", "Adam Shai", "Mark Schnitzer", "Hidenori Tanaka"], "accepted": true, "keywords": ["brain-machine interfaces", "recurrent neural networks", "convex optimization", "computational neuroscience"], "conference": "NeurIPS 2023", "reviews": [{"IS_META_REVIEW": false, "comments": "SUMMARY:\nThe motivation behind this paper is to replace FORCE/RLS fitting of biologically-flavored RNNs to data by a faster and more robust alternative training scheme. This is accomplished by 1) altering the training objective to a cross-entropy loss; 2) using an approximate pre-computable Hessian to facilitate the use of Newton steps; 3) use of a suitable fixed point initialization; 4) using teacher forcing (training only one-step losses); 5) employing ADMM to enforce constraints (e.g., no self-excitation). Experiments show improvements to various metrics, including accuracy of recovered weights, fits to observed activity, and runtime. \n\nThe stated goal of the project is to produce a method fast enough for real-time analysis, though this work focuses only on weight inference and fitting accuracy of the firing rates. Still these models are increasingly used in the field to fit neural data, so better algorithms for doing so are needed.\n\nSTRENGTHS:\n- Good algorithm performance as assessed along multiple dimensions (speed, inference accuracy, reconstruction accuracy).\n- Thoughtful comparisons to other baseline models.\n- Emphasis on real-time and streaming settings.\n- Experiments targeting model mismatch.\n- ADMM approach allows for many different types of potential constraints.\n\nWEAKNESSES:\n- Addresses some key sources of potential model error but not others (e.g., correlated noise, wrong nonlinearity, mismatch between network timescale and measurement timescale for some data types).\n- No experiments on real data. Even if accuracy of weight recovery is impossible to assess, reconstruction accuracy would be.\n\nQUESTIONS:\n- It is unclear to me what the difference is between panels A and B of Figure 3. Just different parameters? It would help if this were reflected in the titles.\n- Figure 4: I realize that the authors would like to zoom in to show differences between models, but the choice of y axis range obscures the fact that these are modest to minor differences between the models.\n- The authors use correlation between the true and inferred weights as their accuracy measure, but this (so far as I can see) first noted in the caption to Figure 4, even though it occurs in Figure 3.\n\nLIMITATIONS:\n1. Equation (1) is not the usual form for the equations defining these networks (e.g., refs 22, 24). Typically, the leak term is on the voltage variable, not the firing rate, and the nonlinear transfer is from voltage to firing rate, not input current to effective drive. It looks to me as if this choice is essential to make the cross-entropy convex in $\\theta$. If so, this should be discussed, since it's a qualitatively minor change that has large implications for the feasibility of the approach.\n\n2. As noted above, it seems to me there are five distinct technical pieces, and it is not always clear what is doing the heavy lifting. For instance, Figure 3 (and S3) seems to indicate that initialization in these models is doing a huge amount of work, which is unsurprising but not well emphasized in the text. Better delineation in the main text of which choices are most important to the results would be helpful.", "TITLE": "Official Review", "RECOMMENDATION": 7, "REVIEWER_CONFIDENCE": 5, "SOUNDNESS_CORRECTNESS": 3, "DATE": "2023-06-27"}, {"IS_META_REVIEW": false, "comments": "SUMMARY:\nThe paper introduces a new method for training RNNs that allows fast convergence which could make realtime parameter update possible.\n\nSTRENGTHS:\n- The method conceptually is simple and intuitive.\n- It tackles an important problem which is the time consuming nature and computing intensivity of ML models\n- It achieves impressive results through simple hacks\n- One possible use of this is also quick experimentation with RNN models\n- Outlier detection is included\n\nWEAKNESSES:\n- The methods section is easy to understand until the end of setion 2.3 where there are many equations with variables that are not defined either in the main text or in the SM (any equation in the main text has to be defined very explicitly in the main text). \n- To evaluate the value of this implementation on the proposed application, I would appreciate a comparison of the speed of computation to the sampling rates of data collection and intervention delivery.\n- I would have appreciated results experimenting on real data and comparing neural dynamics computed via this method compared to other methods\n\nQUESTIONS:\nNA\n\nLIMITATIONS:\nNA", "TITLE": "Official Review", "RECOMMENDATION": 8, "REVIEWER_CONFIDENCE": 4, "SOUNDNESS_CORRECTNESS": 4, "DATE": "2023-07-03"}, {"IS_META_REVIEW": false, "comments": "SUMMARY:\nThe paper proposes a convex loss for training data constrained recurrent neural networks (dRNNs). This is achieved by performing the optimization in the $d_{t,i}$ space instead of $r_{t,i}$ space (as defined in the paper) and using cross-entropy instead of $l_2$ loss. The authors discuss that this choice makes the optimization convex, and using a weighting scheme they show that a pre-computed inverse Hessian (using the data correlation) makes the optimization much faster than original BPTT or FORCE algorithms. Results are shown on synthetic chaotic rate networks under model misspecification as well as noise and subsampling. Better accuracies and faster runtimes suggest that CoRNN has desirable properties compared to baselines.\n\nSTRENGTHS:\n* Developing tools for online experimentation and targeted manipulation of brain circuits is a significant problem. Given the current experimental advances in the neuroscience field these tools are in crucial demand to help us understand geometrical and computational properties of the brain networks. This makes the problem considered by this paper timely and significant.\n\n* Arguably one of the main bottlenecks of this online experimentation is fitting/inference time complexity. This paper takes a step towards speeding up the optimization by convexifying the loss and pre-computing objects to avoid additional computational burden.\n\n* The motivation is clear and the presentation of the paper is logical, understandable, and easy to follow.\n\nWEAKNESSES:\nBelow I've included a list of questions and concerns. In summary, I believe that the experimental part of the paper can be improved by a large margin. Specifically since the method is pitched as a general purpose optimization framework it's important to present results on more complex synthetic datasets as well as real neuroscience dataset where the performance of the model is well investigated under various parameter changes. In addition, I think the discussion section can be further improved by being more upfront about the limitations of the work and paths for future work.\n\n> 81 extraction, especially with thousands of neurons, requires GPUs, leaving only the CPU for dRNNs.\n\n* I'm a little confused by this repeating statement, can we not use multiple GPUs? Is this a constraint for the specific hardware you're using or a more fundamental constraint?\n\n* Eq. 1: correct me if I'm wrong but most of the theoretical neuroscience work is done on the equation where the nonlinearity is applied pre-summation $\\tau \\frac{dr_i}{dt} = -r_i + \\sum w_{ij} \\phi(r_j)$. Although from a model capacity perspective, the two models are shown to have similar capacities the one I included here is more biologically relevant. Can this be implemented in your approach and can you include some results on this alternative model? \n\n* Related to this, the framework seems to heavily rely on the specific instantiation of the network dynamics. For example, given a different form, we cannot immediately consider the loss form of $d_{t,i}$ and use its linear+sigmoid form. This seems to be an important limitation and some discussion on how to extend this to other forms of ODE would be helpful.\n\n\n> 114 $d_{t,i} = \\tanh(\\hat{z})$\n\n* Should it be $\\hat{z}_{t,i}$?\n\n\n* Why is (5) convex with respect to $\\theta$? Is this a trivial fact that the authors leave it unexplained?\n\n* Equation 7 is playing a crucial role in the optimization, can the authors bring the proof to the main text instead of SM?\n\n* Based on (S4), we can in principle use other nonlinearities and a corresponding weighting function $c_{t,i}$ right?\n\n\n**Figures**\n\n* Fig. 1 seems to be over-promising. Although in principle dRNNs can lead to the applications that are discussed but those are not shown in the current work. Unless those applications are not shown in real data/simulations I recommend rewording/having a more concise Fig. 1 that focuses on the contributions. Usually, Fig. 1 is a schematic of what's done in the paper, not an idealistic scenario that can be done in future studies.\n\n* Fig. 3: The colors are very hard to see, specifically because the error bars are too small, can the authors change the formatting to make it easier to read? After reading this paper two times I'm still unsure what \"teacher enforcing\" means in this context and how it's achieved in various percentages. Instead of these two parameter configurations, can the authors show these as line plots when changing the parameters more continuously on a certain range that includes the performance extremes? Related to this, are the claims true about this specific instantiation of the network or does it hold if we change the noise model? For example, intuitively, cross-entropy loss corresponds to the log probability of a categorical distribution, and as the authors show it provides a better surrogate for the data generated from normal distribution. What if we change the noise model to something like a Poisson or some noise model that's not independent across different time points?\n\n* Does the result hold if we change the dynamical regime of the network? In neuroscience, previous work has hypothesized various network mechanisms such as limit cycles, multi-stability, input-driven networks, transitions between multiple attractors, etc. Is it possible to show results on these other regimes to ensure that the presented optimization framework is not beneficial for a particular regime? Can the authors include experiments with varying the dimension of the chaotic attractor or a more complex data-generating model as opposed to a simple chaotic (low-d) rate network? \n\n* Fig. 4B: The result is a little surprising for me, how can the accuracy go down for other methods? Aren't all of these methods guaranteed to converge to a local minimum? Are the authors controlling for the initialization of the parameters?\n\n* Are the times reported in Fig. 4 CPU times or GPU times? \n\n* Fig. 5: In (A) there are these weird bumps/spikes in the network output. It looks like the errors are happening in a space that's not within the null space of the output. Whereas my experience with the flip-flop task is that BPTT errors don't look weird like this. Is this due to the specific architecture chosen or is this a result of the convex loss/optimization framework?\n\n* Fig. 7: miss-matched -> mismatched\n\n* I'm again surprised that the network can account for the common inputs/unobserved nodes. I think it's an established fact that by just using observational data no method can generically recover the weights in the presence of common inputs and unobserved nodes. This might be the result of the specific data-generating model that's used here. A discussion on this would be helpful to point to the limitations of the work.\n\n* Although the work is motivated by neuroscience data and experiments, no experimental data is included in the paper and that to me is the biggest weakness of the paper. Brain data is much more complex and heterogenous and the noise model, nonlinearity, dynamical regimes, and other factors make it harder to build a robust estimator that generalizes to test trials/test time points. I would assume that various loss functions have different properties that make them more suitable to specific datasets and it's hard for me to believe that a single loss can improve loss on all datasets. Unless results on more complex datasets and simulations are shown it's hard to decide whether the presented framework is preferred to the traditional ones.\n\nQUESTIONS:\n* How are the $d_t$'s initialized to be close to the true ones?\n\n* Since the Hessian is not the exact Hessian, does the optimization still guaranteed to find the (local) minimum? Or is it biased? Can the authors use debiasing strategies to account for the Hessian mismatch?\n\n> 128 $\\mathcal{L}_{\\text{CoRNN}} = \\sum_i \\mathcal{L}_i(\\hat{\\theta}_i)$.\n\n* Is this a trivial fact? Is $\\hat{\\theta}_{:,i}$ a specific row/column of the weight matrices? This basically means the optimization problem is separable over different rows/columns. This intuitively sounds unrealistic to me unless again I'm missing something important here.\n\n> 111 [...] This turns the potentially infinite time problem into a single time-step one.\n\n* How is this done? The parameters of the model are still $\\theta$. If the loss sums over all $t,i$ then the gradients with respect to $\\theta$ are still computed in a similar fashion to before unless I'm missing something important here.\n\n> 122 $c_{t,i}=[1-d_{t,i}^2]^{-1}$.\n\n* How is this chosen? This means that some neurons/time points are contributing more to the loss and they are more important to be captured properly, right? Why is this a good choice as opposed to treating all neurons/time points the same?\n\nLIMITATIONS:\nSee weaknesses section", "TITLE": "Official Review", "RECOMMENDATION": 5, "REVIEWER_CONFIDENCE": 3, "SOUNDNESS_CORRECTNESS": 3, "DATE": "2023-07-05"}, {"IS_META_REVIEW": false, "comments": "SUMMARY:\nThe authors introduce a method to produce a digital twin of a biological neural network that can be inferred from measurements of neuronal activity.  The major advantage of the model is that it can be trained in real time to gain the basic dynamics of neural population. In the future this could allow advance HRI applications, like linking brain activity to controlling prosthesis.\n\nThe digital twin is trained using a randomised neural network that represents a neural population. It is used as a teacher network for student network that has a specific structure, designed in a way this is allows approximate convexification of the optimisation problem, enabling a ridiculously easy training of the network that can scale to large neural populations.  The computational cost of performing the analysis of the biological neural network scales linearly with its size.\n\nThe system is evaluated by a test, where a random neural network is initialised repeatedly with Gaussian random weights in a range that can produce also chaotic self-sustained signalling. The is assumed to provide a large enough variation for a neural signal generator\n\nSTRENGTHS:\nThe real time, fast learning capability of the suggested architecture. The convexificaiton, as a technology. has definitely uses and application potential beyond the domain of the paper.\n\nExcellent figures to clarify the process.\n\nWEAKNESSES:\nThe reasoning about the enforced use of CPU does not sound convincing to me. See the question part.\n\nQUESTIONS:\non line 81: Why would the GPU use of real time acquisition of thousands of cell signals would force the dRNN calculation to CPUs? As these are tasks that can be pipelined,  the obvious answer is to use more GPUs .  Also, on can expect that signal detection part will be moved to special purpose chips tuned for inference as the signal dimension grows. \n\nThere has been a recent article (https://doi.org/10.1038/s41598-022-25421-w, published Jan 2023 ) on data-driven modelling of C. elegans brain with different recurrent neural networks architectures that found that 4-hidden layer GRU is able to accurately reproduce the stimuli. As this is based on comparing measured data to artificial neural network behaviour like in the current manuscript, without the real time acceleration, but using  back propagation training, it would be a very good test case for the advantages of using the CoRNN.\nPerhaps the Authors could add this to their submission.\n\nLIMITATIONS:\nNA", "TITLE": "Official Review", "RECOMMENDATION": 8, "REVIEWER_CONFIDENCE": 4, "SOUNDNESS_CORRECTNESS": 4, "DATE": "2023-07-07"}, {"IS_META_REVIEW": true, "comments": "DECISION:\nAccept (poster)\n\nCOMMENT:\nThe heart of this work is to provide a convex approximation to RNN learning where the learning is reduced in complexity to the point where dynamical systems can be learned online. The primary points are to 1) replace the full cost with a \"step-by-step\" cost wherein the dynamics are learned between every two pairs of measurements instead of learning a full sequence that matches the data at all points and 2) replace the standard cost with a cross entropy cost. Given these changes the authors show that the dynamics can be learned efficiently even at scale.\n\nThe work has many merits in terms of the goals and methods. The main detriments came in the form of confusion brought on by the terminology and presentation, that the authors were able to respond to in the response period. To add to this discussion from the AC point, the \"teacher\" terminology is confusing since full-FORCE (DePasquale et al. 2018 PLOS ONE) uses a \"teacher\" network that serves a distinctly different role that also minimizes instability during learning (this work should also probably be cited). There is also some commentary about vanilla RNNs being interpretable, which is a point still up for debate. I believe with the appropriate clarification changes promised by the authors, this work can be a nice addition to the NeurIPS conference and I thus recommend this work be accepted.", "RECOMMENDATION": "Accept (poster)", "TITLE": "Decision", "DATE": "2023-09-21"}], "histories": []}
